ithopy/__init__.py
ithopy/base_message_builder.py
ithopy/base_message_parser.py
ithopy/constants.py
ithopy/exceptions.py
ithopy/message.py
ithopy/devices/__init__.py
ithopy/devices/hru_device.py
ithopy/devices/hru_message_builder.py
ithopy/devices/hru_message_parser.py
ithopy/payloads/__init__.py
ithopy/payloads/base_payload.py
ithopy/payloads/config_payload.py
ithopy/payloads/data_format.py
ithopy/payloads/device_status_payload.py
ithopy/payloads/status_format_payload.py
ithopy/payloads/unknown_payload.py
ithopy-0.2.3.dist-info/LICENSE
ithopy-0.2.3.dist-info/METADATA
ithopy-0.2.3.dist-info/WHEEL
ithopy-0.2.3.dist-info/top_level.txt
ithopy-0.2.3.dist-info/RECORD
