Metadata-Version: 2.1
Name: ithopy
Version: 0.2.3
Summary: IthoPy is a library to communicate with I2C Itho devices
Home-page: https://github.com/philipkocanda/ithopy
Download-URL: https://github.com/philipkocanda/ithopy/archive/refs/tags/v0.2.3.zip
Author: Philip Kocanda
Author-email: philip@kocanda.nl
License: MIT
Keywords: itho,i2c
Classifier: Development Status :: 3 - Alpha
Classifier: Intended Audience :: Developers
Classifier: Topic :: Software Development :: Build Tools
Classifier: License :: OSI Approved :: MIT License
Classifier: Programming Language :: Python :: 3
Classifier: Programming Language :: Python :: 3.9
Classifier: Programming Language :: Python :: 3.10
Classifier: Programming Language :: Python :: 3.11
Classifier: Programming Language :: Python :: 3.12
Requires-Python: >=3.11
License-File: LICENSE
